LICENSE
MANIFEST.in
README.md
pyproject.toml
setup.cfg
setup.py
django_solr/__init__.py
django_solr/admin.py
django_solr/apps.py
django_solr/models.py
django_solr/urls.py
django_solr/views.py
django_solr/django_solr/templates/index_list.html
django_solr/dsl/__init__.py
django_solr/dsl/backend.py
django_solr/dsl/exception.py
django_solr/dsl/fields.py
django_solr/dsl/indexes.py
django_solr/dsl/__pycache__/__init__.cpython-39.pyc
django_solr/dsl/__pycache__/backend.cpython-39.pyc
django_solr/dsl/__pycache__/exception.cpython-39.pyc
django_solr/dsl/__pycache__/fields.cpython-39.pyc
django_solr/dsl/__pycache__/indexes.cpython-39.pyc
django_solr/migrations/0001_initial.py
django_solr/migrations/__init__.py
django_solr/templates/admin/change_list.html
django_solr/templates/admin/django_solr/indexes/change_list.html
django_solr/templates/django_solr/index_list.html
django_solr_dsl.egg-info/PKG-INFO
django_solr_dsl.egg-info/SOURCES.txt
django_solr_dsl.egg-info/dependency_links.txt
django_solr_dsl.egg-info/requires.txt
django_solr_dsl.egg-info/top_level.txt